{
  "npcId": 1540,
  "drops": [
    {
      "itemId": 1333,
      "minAmount": 1,
      "maxAmount": 1,
      "rate": 300
    },
    {
      "itemId": 263,
      "minAmount": 1,
      "maxAmount": 1,
      "rate": 300
    },
    {
      "itemId": 265,
      "minAmount": 1,
      "maxAmount": 1,
      "rate": 300
    },
    {
      "itemId": 267,
      "minAmount": 1,
      "maxAmount": 1,
      "rate": 300
    },
    {
      "itemId": 2481,
      "minAmount": 1,
      "maxAmount": 1,
      "rate": 722
    },
    {
      "itemId": 261,
      "minAmount": 1,
      "maxAmount": 1,
      "rate": 3340
    },
    {
      "itemId": 444,
      "minAmount": 1,
      "maxAmount": 1,
      "rate": 4422
    },
    {
      "itemId": 1391,
      "minAmount": 1,
      "maxAmount": 1,
      "rate": 4646
    },
    {
      "itemId": 1181,
      "minAmount": 1,
      "maxAmount": 1,
      "rate": 4850
    },
    {
      "itemId": 11341,
      "minAmount": 1,
      "maxAmount": 1,
      "rate": 31378
    },
    {
      "itemId": 255,
      "minAmount": 1,
      "maxAmount": 1,
      "rate": 33364
    },
    {
      "itemId": 257,
      "minAmount": 1,
      "maxAmount": 1,
      "rate": 35395
    },
    {
      "itemId": 259,
      "minAmount": 1,
      "maxAmount": 1,
      "rate": 36247
    },
    {
      "itemId": 9418,
      "minAmount": 2,
      "maxAmount": 2,
      "rate": 39794
    },
    {
      "itemId": 2356,
      "minAmount": 3,
      "maxAmount": 3,
      "rate": 62311
    },
    {
      "itemId": 995,
      "minAmount": 2120,
      "maxAmount": 2840,
      "rate": 63475
    },
    {
      "itemId": 249,
      "minAmount": 1,
      "maxAmount": 1,
      "rate": 66855
    },
    {
      "itemId": 253,
      "minAmount": 1,
      "maxAmount": 1,
      "rate": 67575
    },
    {
      "itemId": 251,
      "minAmount": 1,
      "maxAmount": 1,
      "rate": 75806
    },
    {
      "itemId": 2354,
      "minAmount": 3,
      "maxAmount": 3,
      "rate": 78994
    },
    {
      "itemId": 526,
      "minAmount": 1,
      "maxAmount": 1,
      "rate": 100000
    }
  ]
}