{
  "npcId": 2235,
  "drops": [
    {
      "itemId": 1183,
      "minAmount": 1,
      "maxAmount": 1,
      "rate": 3227
    },
    {
      "itemId": 1163,
      "minAmount": 1,
      "maxAmount": 1,
      "rate": 3299
    },
    {
      "itemId": 5280,
      "minAmount": 1,
      "maxAmount": 1,
      "rate": 3390
    },
    {
      "itemId": 213,
      "minAmount": 1,
      "maxAmount": 1,
      "rate": 3617
    },
    {
      "itemId": 5295,
      "minAmount": 1,
      "maxAmount": 1,
      "rate": 3728
    },
    {
      "itemId": 211,
      "minAmount": 1,
      "maxAmount": 1,
      "rate": 3785
    },
    {
      "itemId": 5304,
      "minAmount": 1,
      "maxAmount": 1,
      "rate": 3835
    },
    {
      "itemId": 5300,
      "minAmount": 1,
      "maxAmount": 1,
      "rate": 3953
    },
    {
      "itemId": 207,
      "minAmount": 1,
      "maxAmount": 1,
      "rate": 4601
    },
    {
      "itemId": 217,
      "minAmount": 1,
      "maxAmount": 1,
      "rate": 4737
    },
    {
      "itemId": 5296,
      "minAmount": 1,
      "maxAmount": 1,
      "rate": 4799
    },
    {
      "itemId": 215,
      "minAmount": 1,
      "maxAmount": 1,
      "rate": 4882
    },
    {
      "itemId": 209,
      "minAmount": 1,
      "maxAmount": 1,
      "rate": 4901
    },
    {
      "itemId": 5282,
      "minAmount": 1,
      "maxAmount": 1,
      "rate": 4990
    },
    {
      "itemId": 2485,
      "minAmount": 1,
      "maxAmount": 1,
      "rate": 4996
    },
    {
      "itemId": 869,
      "minAmount": 12,
      "maxAmount": 25,
      "rate": 20224
    },
    {
      "itemId": 1295,
      "minAmount": 1,
      "maxAmount": 1,
      "rate": 20905
    },
    {
      "itemId": 1141,
      "minAmount": 1,
      "maxAmount": 1,
      "rate": 27685
    },
    {
      "itemId": 1197,
      "minAmount": 1,
      "maxAmount": 1,
      "rate": 30787
    },
    {
      "itemId": 1071,
      "minAmount": 1,
      "maxAmount": 1,
      "rate": 30834
    },
    {
      "itemId": 809,
      "minAmount": 12,
      "maxAmount": 25,
      "rate": 31000
    },
    {
      "itemId": 1211,
      "minAmount": 1,
      "maxAmount": 1,
      "rate": 31126
    },
    {
      "itemId": 1209,
      "minAmount": 1,
      "maxAmount": 1,
      "rate": 31642
    },
    {
      "itemId": 1430,
      "minAmount": 1,
      "maxAmount": 1,
      "rate": 31642
    },
    {
      "itemId": 1313,
      "minAmount": 1,
      "maxAmount": 1,
      "rate": 31749
    },
    {
      "itemId": 1329,
      "minAmount": 1,
      "maxAmount": 1,
      "rate": 33162
    },
    {
      "itemId": 5293,
      "minAmount": 1,
      "maxAmount": 1,
      "rate": 35426
    },
    {
      "itemId": 1311,
      "minAmount": 1,
      "maxAmount": 1,
      "rate": 38193
    },
    {
      "itemId": 1299,
      "minAmount": 1,
      "maxAmount": 1,
      "rate": 38751
    },
    {
      "itemId": 1365,
      "minAmount": 1,
      "maxAmount": 1,
      "rate": 60089
    },
    {
      "itemId": 1119,
      "minAmount": 1,
      "maxAmount": 1,
      "rate": 60911
    },
    {
      "itemId": 1217,
      "minAmount": 1,
      "maxAmount": 1,
      "rate": 61431
    },
    {
      "itemId": 1105,
      "minAmount": 1,
      "maxAmount": 1,
      "rate": 66983
    },
    {
      "itemId": 1101,
      "minAmount": 1,
      "maxAmount": 1,
      "rate": 67297
    },
    {
      "itemId": 869,
      "minAmount": 4,
      "maxAmount": 22,
      "rate": 68170
    },
    {
      "itemId": 1105,
      "minAmount": 1,
      "maxAmount": 1,
      "rate": 69500
    },
    {
      "itemId": 995,
      "minAmount": 60,
      "maxAmount": 9460,
      "rate": 70555
    },
    {
      "itemId": 1207,
      "minAmount": 1,
      "maxAmount": 1,
      "rate": 71063
    },
    {
      "itemId": 1297,
      "minAmount": 1,
      "maxAmount": 1,
      "rate": 71211
    },
    {
      "itemId": 1309,
      "minAmount": 1,
      "maxAmount": 1,
      "rate": 71384
    },
    {
      "itemId": 1165,
      "minAmount": 1,
      "maxAmount": 1,
      "rate": 75228
    },
    {
      "itemId": 1283,
      "minAmount": 1,
      "maxAmount": 1,
      "rate": 76360
    },
    {
      "itemId": 1424,
      "minAmount": 1,
      "maxAmount": 1,
      "rate": 77145
    },
    {
      "itemId": 1426,
      "minAmount": 1,
      "maxAmount": 1,
      "rate": 77650
    },
    {
      "itemId": 1281,
      "minAmount": 1,
      "maxAmount": 1,
      "rate": 77932
    },
    {
      "itemId": 379,
      "minAmount": 1,
      "maxAmount": 1,
      "rate": 79145
    },
    {
      "itemId": 532,
      "minAmount": 1,
      "maxAmount": 1,
      "rate": 100000
    }
  ]
}