{
  "npcId": 5682,
  "drops": [
    {
      "itemId": 3367,
      "minAmount": 3,
      "maxAmount": 3,
      "rate": 20241
    },
    {
      "itemId": 1291,
      "minAmount": 1,
      "maxAmount": 1,
      "rate": 21444
    },
    {
      "itemId": 886,
      "minAmount": 5,
      "maxAmount": 5,
      "rate": 25746
    },
    {
      "itemId": 3365,
      "minAmount": 1,
      "maxAmount": 1,
      "rate": 26469
    },
    {
      "itemId": 558,
      "minAmount": 5,
      "maxAmount": 5,
      "rate": 26620
    },
    {
      "itemId": 1139,
      "minAmount": 1,
      "maxAmount": 1,
      "rate": 30956
    },
    {
      "itemId": 884,
      "minAmount": 5,
      "maxAmount": 5,
      "rate": 34742
    },
    {
      "itemId": 3363,
      "minAmount": 1,
      "maxAmount": 1,
      "rate": 36901
    },
    {
      "itemId": 10941,
      "minAmount": 1,
      "maxAmount": 1,
      "rate": 63937
    },
    {
      "itemId": 10939,
      "minAmount": 1,
      "maxAmount": 1,
      "rate": 66936
    },
    {
      "itemId": 10940,
      "minAmount": 1,
      "maxAmount": 1,
      "rate": 71675
    },
    {
      "itemId": 10933,
      "minAmount": 1,
      "maxAmount": 1,
      "rate": 79253
    },
    {
      "itemId": 526,
      "minAmount": 1,
      "maxAmount": 1,
      "rate": 100000
    },
    {
      "itemId": 960,
      "minAmount": 1,
      "maxAmount": 1,
      "rate": 100000
    }
  ]
}