{
  "npcId": 6392,
  "drops": [
    {
      "itemId": 5302,
      "minAmount": 1,
      "maxAmount": 1,
      "rate": 300
    },
    {
      "itemId": 5304,
      "minAmount": 1,
      "maxAmount": 1,
      "rate": 300
    },
    {
      "itemId": 5300,
      "minAmount": 1,
      "maxAmount": 1,
      "rate": 474
    },
    {
      "itemId": 5303,
      "minAmount": 1,
      "maxAmount": 1,
      "rate": 509
    },
    {
      "itemId": 5301,
      "minAmount": 1,
      "maxAmount": 1,
      "rate": 932
    },
    {
      "itemId": 5299,
      "minAmount": 1,
      "maxAmount": 1,
      "rate": 3017
    },
    {
      "itemId": 5296,
      "minAmount": 1,
      "maxAmount": 1,
      "rate": 3384
    },
    {
      "itemId": 5295,
      "minAmount": 1,
      "maxAmount": 1,
      "rate": 3621
    },
    {
      "itemId": 5106,
      "minAmount": 1,
      "maxAmount": 1,
      "rate": 3653
    },
    {
      "itemId": 5294,
      "minAmount": 1,
      "maxAmount": 1,
      "rate": 3795
    },
    {
      "itemId": 5280,
      "minAmount": 1,
      "maxAmount": 1,
      "rate": 3872
    },
    {
      "itemId": 5105,
      "minAmount": 1,
      "maxAmount": 1,
      "rate": 3937
    },
    {
      "itemId": 5298,
      "minAmount": 1,
      "maxAmount": 1,
      "rate": 4340
    },
    {
      "itemId": 1181,
      "minAmount": 1,
      "maxAmount": 1,
      "rate": 4349
    },
    {
      "itemId": 5297,
      "minAmount": 1,
      "maxAmount": 1,
      "rate": 4454
    },
    {
      "itemId": 5281,
      "minAmount": 1,
      "maxAmount": 1,
      "rate": 4560
    },
    {
      "itemId": 5282,
      "minAmount": 1,
      "maxAmount": 1,
      "rate": 4627
    },
    {
      "itemId": 5321,
      "minAmount": 1,
      "maxAmount": 1,
      "rate": 4947
    },
    {
      "itemId": 1141,
      "minAmount": 1,
      "maxAmount": 1,
      "rate": 21183
    },
    {
      "itemId": 209,
      "minAmount": 1,
      "maxAmount": 1,
      "rate": 24331
    },
    {
      "itemId": 203,
      "minAmount": 1,
      "maxAmount": 1,
      "rate": 26032
    },
    {
      "itemId": 1341,
      "minAmount": 1,
      "maxAmount": 1,
      "rate": 26175
    },
    {
      "itemId": 5323,
      "minAmount": 1,
      "maxAmount": 1,
      "rate": 26287
    },
    {
      "itemId": 5104,
      "minAmount": 1,
      "maxAmount": 1,
      "rate": 26406
    },
    {
      "itemId": 5292,
      "minAmount": 1,
      "maxAmount": 1,
      "rate": 26941
    },
    {
      "itemId": 5293,
      "minAmount": 1,
      "maxAmount": 1,
      "rate": 29086
    },
    {
      "itemId": 199,
      "minAmount": 1,
      "maxAmount": 1,
      "rate": 30048
    },
    {
      "itemId": 1339,
      "minAmount": 1,
      "maxAmount": 1,
      "rate": 31617
    },
    {
      "itemId": 561,
      "minAmount": 1,
      "maxAmount": 7,
      "rate": 32104
    },
    {
      "itemId": 5311,
      "minAmount": 1,
      "maxAmount": 1,
      "rate": 34048
    },
    {
      "itemId": 557,
      "minAmount": 25,
      "maxAmount": 60,
      "rate": 34232
    },
    {
      "itemId": 5100,
      "minAmount": 1,
      "maxAmount": 1,
      "rate": 38847
    },
    {
      "itemId": 995,
      "minAmount": 100,
      "maxAmount": 2000,
      "rate": 60070
    },
    {
      "itemId": 453,
      "minAmount": 3,
      "maxAmount": 3,
      "rate": 78248
    },
    {
      "itemId": 526,
      "minAmount": 1,
      "maxAmount": 1,
      "rate": 100000
    }
  ]
}