{
  "npcId": 7686,
  "drops": [
    {
      "itemId": 1623,
      "minAmount": 1,
      "maxAmount": 1,
      "rate": 3123
    },
    {
      "itemId": 1619,
      "minAmount": 1,
      "maxAmount": 1,
      "rate": 4668
    },
    {
      "itemId": 1755,
      "minAmount": 1,
      "maxAmount": 1,
      "rate": 60171
    },
    {
      "itemId": 6529,
      "minAmount": 1,
      "maxAmount": 16,
      "rate": 68274
    },
    {
      "itemId": 1935,
      "minAmount": 1,
      "maxAmount": 1,
      "rate": 70868
    },
    {
      "itemId": 2347,
      "minAmount": 1,
      "maxAmount": 1,
      "rate": 72358
    },
    {
      "itemId": 1931,
      "minAmount": 1,
      "maxAmount": 1,
      "rate": 75945
    },
    {
      "itemId": 946,
      "minAmount": 1,
      "maxAmount": 1,
      "rate": 79244
    }
  ]
}