{
  "id": 4395,
  "hitpoints": 1,
  "attackSpeed": 4,
  "slayerLevel": 0,
  "attackDistance": 8,
  "aggressionDistance": 8,
  "maximumDistance": 16,
  "targetType": "PLAYER",
  "immunityTypes": [
    "POISON",
    "VENOM"
  ],
  "statDefinitions": {
    "combatStats": [
      1,
      1,
      1,
      1,
      1
    ],
    "aggressiveStats": [
      0,
      0,
      0,
      0,
      0
    ],
    "defensiveStats": [
      0,
      0,
      0,
      0,
      0
    ],
    "otherBonuses": [
      0,
      0,
      0
    ]
  },
  "attackDefinitions": {
    "type": "MAGIC",
    "maxHit": 20,
    "animation": {
      "id": 359,
      "delay": 0
    }
  },
  "blockDefinitions": {
    "animation": {
      "id": 360,
      "delay": 0
    }
  },
  "spawnDefinitions": {
    "respawnDelay": 25,
    "deathAnimation": {
      "id": 361,
      "delay": 0
    },
    "spawnAnimation": {
      "id": -1,
      "delay": 0
    }
  }
}