{
  "id": 7532,
  "hitpoints": 200,
  "attackSpeed": 3,
  "slayerLevel": 0,
  "attackDistance": 4,
  "aggressionDistance": 4,
  "maximumDistance": 16,
  "targetType": "PLAYER",
  "aggressionType": "AGGRESSIVE",
  "toxinDefinitions": {
    "type": "POISON",
    "damage": 20
  },
  "statDefinitions": {
    "combatStats": [
      150,
      150,
      88,
      88,
      150
    ],
    "aggressiveStats": [
      0,
      0,
      0,
      0,
      0
    ],
    "defensiveStats": [
      0,
      0,
      0,
      70,
      60
    ],
    "otherBonuses": [
      0,
      0,
      0
    ]
  },
  "attackDefinitions": {
    "type": "RANGED",
    "maxHit": 0,
    "animation": {
      "id": 7450,
      "delay": 0
    }
  },
  "blockDefinitions": {
    "animation": {
      "id": 7451,
      "delay": 0
    }
  },
  "spawnDefinitions": {
    "respawnDelay": 25,
    "deathAnimation": {
      "id": 7458,
      "delay": 0
    },
    "spawnAnimation": {
      "id": -1,
      "delay": 0
    }
  }
}